{"action":{"identity":{"address":"N\u0000sourcecred\u0000core\u0000IDENTITY\u0000CjFxFz7M71WMV1Qr5qmOJQ\u0000","aliases":[],"id":"CjFxFz7M71WMV1Qr5qmOJQ","name":"decentralion","subtype":"USER"},"type":"CREATE_IDENTITY"},"ledgerTimestamp":1646939606361,"uuid":"RSpSQfzjVwSgqbQAz8XvkA","version":"1"}
{"action":{"alias":{"address":"N\u0000sourcecred\u0000github\u0000USERLIKE\u0000USER\u0000decentralion\u0000","description":"github/[@decentralion](https://github.com/decentralion)"},"identityId":"CjFxFz7M71WMV1Qr5qmOJQ","type":"ADD_ALIAS"},"ledgerTimestamp":1646939606362,"uuid":"qhVnclvWzUxjbMBAvpZuGw","version":"1"}
{"action":{"identity":{"address":"N\u0000sourcecred\u0000core\u0000IDENTITY\u0000d61bwjJlfk6nNTBU3yzbSw\u0000","aliases":[],"id":"d61bwjJlfk6nNTBU3yzbSw","name":"credbot","subtype":"BOT"},"type":"CREATE_IDENTITY"},"ledgerTimestamp":1646939606363,"uuid":"6KrSLXuE3jBvALNdiZFPgA","version":"1"}
{"action":{"alias":{"address":"N\u0000sourcecred\u0000github\u0000USERLIKE\u0000BOT\u0000credbot\u0000","description":"github/[@credbot](https://github.com/credbot)"},"identityId":"d61bwjJlfk6nNTBU3yzbSw","type":"ADD_ALIAS"},"ledgerTimestamp":1646939606363,"uuid":"1Sduq4IyiVVoJOD6lJrkvw","version":"1"}
{"action":{"identity":{"address":"N\u0000sourcecred\u0000core\u0000IDENTITY\u0000xHoiordd6PvOe31Got0veA\u0000","aliases":[],"id":"xHoiordd6PvOe31Got0veA","name":"wchargin","subtype":"USER"},"type":"CREATE_IDENTITY"},"ledgerTimestamp":1646939606363,"uuid":"RzBAbVnD7BJFMCX8MHj43w","version":"1"}
{"action":{"alias":{"address":"N\u0000sourcecred\u0000github\u0000USERLIKE\u0000USER\u0000wchargin\u0000","description":"github/[@wchargin](https://github.com/wchargin)"},"identityId":"xHoiordd6PvOe31Got0veA","type":"ADD_ALIAS"},"ledgerTimestamp":1646939606363,"uuid":"ikFpKpqSR5L7a9YzbF757A","version":"1"}
{"action":{"identity":{"address":"N\u0000sourcecred\u0000core\u0000IDENTITY\u00004KO9Ok9vBEwMuk1zjsOtkg\u0000","aliases":[],"id":"4KO9Ok9vBEwMuk1zjsOtkg","name":"SourceCred","subtype":"PROJECT"},"type":"CREATE_IDENTITY"},"ledgerTimestamp":1646939606400,"uuid":"v6YAVYcxyEHoyxypGR7Lnw","version":"1"}
{"action":{"identityId":"4KO9Ok9vBEwMuk1zjsOtkg","type":"TOGGLE_ACTIVATION"},"ledgerTimestamp":1646939606400,"uuid":"CVKXyeD3BlNRPqewP5Xovg","version":"1"}
{"action":{"identity":{"address":"N\u0000sourcecred\u0000core\u0000IDENTITY\u0000YEVYT3foRzhQxDrmecDC4w\u0000","aliases":[],"id":"YEVYT3foRzhQxDrmecDC4w","name":"sjdthree","subtype":"USER"},"type":"CREATE_IDENTITY"},"ledgerTimestamp":1650764457158,"uuid":"G8Kmd1wvypo7Q2hRgyH3lQ","version":"1"}
{"action":{"alias":{"address":"N\u0000sourcecred\u0000github\u0000USERLIKE\u0000USER\u0000sjdthree\u0000","description":"github/[@sjdthree](https://github.com/sjdthree)"},"identityId":"YEVYT3foRzhQxDrmecDC4w","type":"ADD_ALIAS"},"ledgerTimestamp":1650764457158,"uuid":"gIX7Xv20iJcrLJA04GIyBQ","version":"1"}
{"action":{"identity":{"address":"N\u0000sourcecred\u0000core\u0000IDENTITY\u0000Q3uRt3jJSpDhlW6kYeKkMg\u0000","aliases":[],"id":"Q3uRt3jJSpDhlW6kYeKkMg","name":"codynhat","subtype":"USER"},"type":"CREATE_IDENTITY"},"ledgerTimestamp":1650764457160,"uuid":"IxJgAf9PnLsLzNomnNlL7w","version":"1"}
{"action":{"alias":{"address":"N\u0000sourcecred\u0000github\u0000USERLIKE\u0000USER\u0000codynhat\u0000","description":"github/[@codynhat](https://github.com/codynhat)"},"identityId":"Q3uRt3jJSpDhlW6kYeKkMg","type":"ADD_ALIAS"},"ledgerTimestamp":1650764457160,"uuid":"KjptpB3w062u9W7AdXqFaw","version":"1"}
{"action":{"identity":{"address":"N\u0000sourcecred\u0000core\u0000IDENTITY\u0000o1pMXm7co2gXjte4iJR4Jw\u0000","aliases":[],"id":"o1pMXm7co2gXjte4iJR4Jw","name":"netlify","subtype":"USER"},"type":"CREATE_IDENTITY"},"ledgerTimestamp":1650764457160,"uuid":"nZMnz0H1YkAHginNoKJwzQ","version":"1"}
{"action":{"alias":{"address":"N\u0000sourcecred\u0000github\u0000USERLIKE\u0000USER\u0000netlify\u0000","description":"github/[@netlify](https://github.com/apps/netlify)"},"identityId":"o1pMXm7co2gXjte4iJR4Jw","type":"ADD_ALIAS"},"ledgerTimestamp":1650764457160,"uuid":"qf02iopQclU5eRzWTKnZkQ","version":"1"}
{"action":{"identity":{"address":"N\u0000sourcecred\u0000core\u0000IDENTITY\u0000AcPYxQX48JwW6fe7Pky9Iw\u0000","aliases":[],"id":"AcPYxQX48JwW6fe7Pky9Iw","name":"maxmandia","subtype":"USER"},"type":"CREATE_IDENTITY"},"ledgerTimestamp":1650764457160,"uuid":"4lvwUOKZ7tgVoqwqJni3Sw","version":"1"}
{"action":{"alias":{"address":"N\u0000sourcecred\u0000github\u0000USERLIKE\u0000USER\u0000maxmandia\u0000","description":"github/[@maxmandia](https://github.com/maxmandia)"},"identityId":"AcPYxQX48JwW6fe7Pky9Iw","type":"ADD_ALIAS"},"ledgerTimestamp":1650764457161,"uuid":"5yGLP1rwbB3FnJL8kbkp8w","version":"1"}
{"action":{"identity":{"address":"N\u0000sourcecred\u0000core\u0000IDENTITY\u0000I8p2xR1zGA5WaLCdgbSEuA\u0000","aliases":[],"id":"I8p2xR1zGA5WaLCdgbSEuA","name":"Shubham0850","subtype":"USER"},"type":"CREATE_IDENTITY"},"ledgerTimestamp":1650764457161,"uuid":"DROWDekmFPRUDnkHLupbow","version":"1"}
{"action":{"alias":{"address":"N\u0000sourcecred\u0000github\u0000USERLIKE\u0000USER\u0000Shubham0850\u0000","description":"github/[@Shubham0850](https://github.com/Shubham0850)"},"identityId":"I8p2xR1zGA5WaLCdgbSEuA","type":"ADD_ALIAS"},"ledgerTimestamp":1650764457163,"uuid":"QtzAdtGXtWWXbeN4Dh5RwQ","version":"1"}
{"action":{"identity":{"address":"N\u0000sourcecred\u0000core\u0000IDENTITY\u0000qe5NGso1JuKt0EjQP5uyxg\u0000","aliases":[],"id":"qe5NGso1JuKt0EjQP5uyxg","name":"Khalizo","subtype":"USER"},"type":"CREATE_IDENTITY"},"ledgerTimestamp":1650764457163,"uuid":"5JlmWQULONhP4UaRptJGnA","version":"1"}
{"action":{"alias":{"address":"N\u0000sourcecred\u0000github\u0000USERLIKE\u0000USER\u0000Khalizo\u0000","description":"github/[@Khalizo](https://github.com/Khalizo)"},"identityId":"qe5NGso1JuKt0EjQP5uyxg","type":"ADD_ALIAS"},"ledgerTimestamp":1650764457164,"uuid":"UxBgaAD4QvzHQOjEA14rRg","version":"1"}
