{"action":{"identity":{"address":"N\u0000sourcecred\u0000core\u0000IDENTITY\u0000CjFxFz7M71WMV1Qr5qmOJQ\u0000","aliases":[],"id":"CjFxFz7M71WMV1Qr5qmOJQ","name":"decentralion","subtype":"USER"},"type":"CREATE_IDENTITY"},"ledgerTimestamp":1646939606361,"uuid":"RSpSQfzjVwSgqbQAz8XvkA","version":"1"}
{"action":{"alias":{"address":"N\u0000sourcecred\u0000github\u0000USERLIKE\u0000USER\u0000decentralion\u0000","description":"github/[@decentralion](https://github.com/decentralion)"},"identityId":"CjFxFz7M71WMV1Qr5qmOJQ","type":"ADD_ALIAS"},"ledgerTimestamp":1646939606362,"uuid":"qhVnclvWzUxjbMBAvpZuGw","version":"1"}
{"action":{"identity":{"address":"N\u0000sourcecred\u0000core\u0000IDENTITY\u0000d61bwjJlfk6nNTBU3yzbSw\u0000","aliases":[],"id":"d61bwjJlfk6nNTBU3yzbSw","name":"credbot","subtype":"BOT"},"type":"CREATE_IDENTITY"},"ledgerTimestamp":1646939606363,"uuid":"6KrSLXuE3jBvALNdiZFPgA","version":"1"}
{"action":{"alias":{"address":"N\u0000sourcecred\u0000github\u0000USERLIKE\u0000BOT\u0000credbot\u0000","description":"github/[@credbot](https://github.com/credbot)"},"identityId":"d61bwjJlfk6nNTBU3yzbSw","type":"ADD_ALIAS"},"ledgerTimestamp":1646939606363,"uuid":"1Sduq4IyiVVoJOD6lJrkvw","version":"1"}
{"action":{"identity":{"address":"N\u0000sourcecred\u0000core\u0000IDENTITY\u0000xHoiordd6PvOe31Got0veA\u0000","aliases":[],"id":"xHoiordd6PvOe31Got0veA","name":"wchargin","subtype":"USER"},"type":"CREATE_IDENTITY"},"ledgerTimestamp":1646939606363,"uuid":"RzBAbVnD7BJFMCX8MHj43w","version":"1"}
{"action":{"alias":{"address":"N\u0000sourcecred\u0000github\u0000USERLIKE\u0000USER\u0000wchargin\u0000","description":"github/[@wchargin](https://github.com/wchargin)"},"identityId":"xHoiordd6PvOe31Got0veA","type":"ADD_ALIAS"},"ledgerTimestamp":1646939606363,"uuid":"ikFpKpqSR5L7a9YzbF757A","version":"1"}
{"action":{"identity":{"address":"N\u0000sourcecred\u0000core\u0000IDENTITY\u00004KO9Ok9vBEwMuk1zjsOtkg\u0000","aliases":[],"id":"4KO9Ok9vBEwMuk1zjsOtkg","name":"SourceCred","subtype":"PROJECT"},"type":"CREATE_IDENTITY"},"ledgerTimestamp":1646939606400,"uuid":"v6YAVYcxyEHoyxypGR7Lnw","version":"1"}
{"action":{"identityId":"4KO9Ok9vBEwMuk1zjsOtkg","type":"TOGGLE_ACTIVATION"},"ledgerTimestamp":1646939606400,"uuid":"CVKXyeD3BlNRPqewP5Xovg","version":"1"}
{"action":{"identity":{"address":"N\u0000sourcecred\u0000core\u0000IDENTITY\u0000jokjwWI7vnx0S6BLOged9Q\u0000","aliases":[],"id":"jokjwWI7vnx0S6BLOged9Q","name":"sjdthree","subtype":"USER"},"type":"CREATE_IDENTITY"},"ledgerTimestamp":1651456656026,"uuid":"zLPzyye3I0kHPNTA5mwDfA","version":"1"}
{"action":{"alias":{"address":"N\u0000sourcecred\u0000github\u0000USERLIKE\u0000USER\u0000sjdthree\u0000","description":"github/[@sjdthree](https://github.com/sjdthree)"},"identityId":"jokjwWI7vnx0S6BLOged9Q","type":"ADD_ALIAS"},"ledgerTimestamp":1651456656026,"uuid":"zy7nCOe6Q97dl13ZDzxkOw","version":"1"}
{"action":{"identity":{"address":"N\u0000sourcecred\u0000core\u0000IDENTITY\u0000hwXF4YWVmXn6dDdlr4jEgw\u0000","aliases":[],"id":"hwXF4YWVmXn6dDdlr4jEgw","name":"codynhat","subtype":"USER"},"type":"CREATE_IDENTITY"},"ledgerTimestamp":1651456656027,"uuid":"a3OangkD307S24vxCoqywA","version":"1"}
{"action":{"alias":{"address":"N\u0000sourcecred\u0000github\u0000USERLIKE\u0000USER\u0000codynhat\u0000","description":"github/[@codynhat](https://github.com/codynhat)"},"identityId":"hwXF4YWVmXn6dDdlr4jEgw","type":"ADD_ALIAS"},"ledgerTimestamp":1651456656027,"uuid":"q3X0W5xxBataQXpnS86Vcg","version":"1"}
{"action":{"identity":{"address":"N\u0000sourcecred\u0000core\u0000IDENTITY\u0000DgpYULLkLzDSmwduVUzwfg\u0000","aliases":[],"id":"DgpYULLkLzDSmwduVUzwfg","name":"netlify","subtype":"USER"},"type":"CREATE_IDENTITY"},"ledgerTimestamp":1651456656027,"uuid":"U3il9M3f4O7HKzqUmBxvPw","version":"1"}
{"action":{"alias":{"address":"N\u0000sourcecred\u0000github\u0000USERLIKE\u0000USER\u0000netlify\u0000","description":"github/[@netlify](https://github.com/apps/netlify)"},"identityId":"DgpYULLkLzDSmwduVUzwfg","type":"ADD_ALIAS"},"ledgerTimestamp":1651456656028,"uuid":"xvWeb5mF9wtxFqXhzyYAhA","version":"1"}
{"action":{"identity":{"address":"N\u0000sourcecred\u0000core\u0000IDENTITY\u0000vaN3z7wh2C052pLpLKURXg\u0000","aliases":[],"id":"vaN3z7wh2C052pLpLKURXg","name":"maxmandia","subtype":"USER"},"type":"CREATE_IDENTITY"},"ledgerTimestamp":1651456656031,"uuid":"POYFwib5ozaZXdwn2z0nyw","version":"1"}
{"action":{"alias":{"address":"N\u0000sourcecred\u0000github\u0000USERLIKE\u0000USER\u0000maxmandia\u0000","description":"github/[@maxmandia](https://github.com/maxmandia)"},"identityId":"vaN3z7wh2C052pLpLKURXg","type":"ADD_ALIAS"},"ledgerTimestamp":1651456656031,"uuid":"IoUReKoMkHmva49uNYw9Vw","version":"1"}
{"action":{"identity":{"address":"N\u0000sourcecred\u0000core\u0000IDENTITY\u0000yDwt1mYzQARmMfoUnqNgkA\u0000","aliases":[],"id":"yDwt1mYzQARmMfoUnqNgkA","name":"Shubham0850","subtype":"USER"},"type":"CREATE_IDENTITY"},"ledgerTimestamp":1651456656032,"uuid":"LjLefn3IY6lk3ndxWEeizQ","version":"1"}
{"action":{"alias":{"address":"N\u0000sourcecred\u0000github\u0000USERLIKE\u0000USER\u0000Shubham0850\u0000","description":"github/[@Shubham0850](https://github.com/Shubham0850)"},"identityId":"yDwt1mYzQARmMfoUnqNgkA","type":"ADD_ALIAS"},"ledgerTimestamp":1651456656032,"uuid":"GVWrG6WyCAhZ7BKYw2uKAw","version":"1"}
{"action":{"identity":{"address":"N\u0000sourcecred\u0000core\u0000IDENTITY\u0000Kd2k6GKo7mZZV6pKvsYLyw\u0000","aliases":[],"id":"Kd2k6GKo7mZZV6pKvsYLyw","name":"Khalizo","subtype":"USER"},"type":"CREATE_IDENTITY"},"ledgerTimestamp":1651456656032,"uuid":"LBzAuriyMZeOsBrRV1kqmw","version":"1"}
{"action":{"alias":{"address":"N\u0000sourcecred\u0000github\u0000USERLIKE\u0000USER\u0000Khalizo\u0000","description":"github/[@Khalizo](https://github.com/Khalizo)"},"identityId":"Kd2k6GKo7mZZV6pKvsYLyw","type":"ADD_ALIAS"},"ledgerTimestamp":1651456656032,"uuid":"AQByTOYejgL0CbqqdAjcnw","version":"1"}
